[
    {
        "balances": {
            "0x02314c": 95, 
            "0x0334ee": 89, 
            "0x0717d7": 91, 
            "0x08fb43": 72, 
            "0x0a1928": 59, 
            "0x0b87e9": 72, 
            "0x112a6c": 50, 
            "0x132118": 11, 
            "0x161a68": 86, 
            "0x192f56": 44, 
            "0x1a58d9": 69, 
            "0x1c18a3": 86, 
            "0x1d500c": 9, 
            "0x2336fe": 6, 
            "0x23f30f": 58, 
            "0x271f93": 68, 
            "0x28de1d": 56, 
            "0x291c87": 27, 
            "0x2951d5": 61, 
            "0x297956": 4, 
            "0x2d8ace": 78, 
            "0x2e5ba8": 79, 
            "0x2f23d6": 13, 
            "0x31da1a": 46, 
            "0x31e37d": 51, 
            "0x32580a": 39, 
            "0x379e95": 50, 
            "0x3a75d8": 96, 
            "0x3aac67": 38, 
            "0x3ab154": 54, 
            "0x3c794f": 55, 
            "0x3d2435": 90, 
            "0x3e21b6": 59, 
            "0x4be911": 79, 
            "0x4cfc3a": 47, 
            "0x4cfca6": 68, 
            "0x4d57fe": 5, 
            "0x4fd760": 94, 
            "0x50853a": 13, 
            "0x525ab7": 2, 
            "0x56929c": 50, 
            "0x58b2aa": 15, 
            "0x6071a6": 86, 
            "0x633253": 84, 
            "0x659792": 85, 
            "0x66d178": 34, 
            "0x67cdcd": 9, 
            "0x6c905a": 61, 
            "0x6d7beb": 94, 
            "0x6d81d2": 10, 
            "0x708308": 5, 
            "0x751267": 52, 
            "0x76b8d4": 58, 
            "0x79a6f2": 16, 
            "0x7e02f2": 97, 
            "0x7ea922": 72, 
            "0x83dd3a": 89, 
            "0x8416c3": 81, 
            "0x86730f": 76, 
            "0x87592c": 18, 
            "0x8a1c55": 92, 
            "0x8e0f45": 74, 
            "0x91febb": 71, 
            "0x93a797": 86, 
            "0x958d15": 38, 
            "0x958d42": 38, 
            "0x9f84a3": 67, 
            "0x9fde51": 34, 
            "0xa210f3": 83, 
            "0xa29662": 78, 
            "0xa2a728": 97, 
            "0xa65b9a": 10, 
            "0xa87234": 19, 
            "0xade9a4": 17, 
            "0xaf9152": 63, 
            "0xb51d18": 80, 
            "0xb78438": 53, 
            "0xb7e6b1": 85, 
            "0xb8e965": 91, 
            "0xba84b6": 99, 
            "0xbd1a1b": 60, 
            "0xbee2de": 12, 
            "0xc05730": 30, 
            "0xc49bd5": 37, 
            "0xc6ffd9": 21, 
            "0xcb6398": 1, 
            "0xd8b894": 45, 
            "0xdac5bd": 50, 
            "0xde0a13": 71, 
            "0xdee16f": 41, 
            "0xdfd5f9": 4, 
            "0xe25388": 70, 
            "0xe356f7": 44, 
            "0xebff4e": 98, 
            "0xf0ef5d": 10, 
            "0xf193e8": 53, 
            "0xf2bdb0": 11, 
            "0xf6a75c": 94, 
            "0xf6c43c": 60, 
            "0xfaf2c4": 7
        }, 
        "hash": "0xba5b35", 
        "number": 0, 
        "prevhash": "0x46e8e7", 
        "transfers": []
    }, 
    {
        "hash": "0x3e6ae3", 
        "number": 1, 
        "prevhash": "0xba5b35", 
        "transfers": [
            {
                "amount": 10, 
                "receiver": "0x3ab154", 
                "sender": "0x28de1d"
            }, 
            {
                "amount": 50, 
                "receiver": "0x4cfc3a", 
                "sender": "0x31e37d"
            }, 
            {
                "amount": 4, 
                "receiver": "0x2e5ba8", 
                "sender": "0x79a6f2"
            }
        ]
    }, 
    {
        "hash": "0xe33fb8", 
        "number": 1, 
        "prevhash": "0xba5b35", 
        "transfers": [
            {
                "amount": 14, 
                "receiver": "0xcb6398", 
                "sender": "0x76b8d4"
            }, 
            {
                "amount": 2, 
                "receiver": "0xdac5bd", 
                "sender": "0xc49bd5"
            }
        ]
    }, 
    {
        "hash": "0xf61b8e", 
        "number": 2, 
        "prevhash": "0xe33fb8", 
        "transfers": [
            {
                "amount": 74, 
                "receiver": "0x8a1c55", 
                "sender": "0x659792"
            }, 
            {
                "amount": 21, 
                "receiver": "0xa29662", 
                "sender": "0x2e5ba8"
            }, 
            {
                "amount": 14, 
                "receiver": "0x3e21b6", 
                "sender": "0xb7e6b1"
            }, 
            {
                "amount": 13, 
                "receiver": "0x0717d7", 
                "sender": "0xa2a728"
            }, 
            {
                "amount": 29, 
                "receiver": "0xa87234", 
                "sender": "0x9f84a3"
            }, 
            {
                "amount": 21, 
                "receiver": "0x2336fe", 
                "sender": "0xaf9152"
            }
        ]
    }, 
    {
        "hash": "0x041e7a", 
        "number": 1, 
        "prevhash": "0xba5b35", 
        "transfers": [
            {
                "amount": 14, 
                "receiver": "0xcb6398", 
                "sender": "0x76b8d4"
            }, 
            {
                "amount": 4, 
                "receiver": "0xa87234", 
                "sender": "0x0717d7"
            }, 
            {
                "amount": 4, 
                "receiver": "0x0717d7", 
                "sender": "0x132118"
            }, 
            {
                "amount": 27, 
                "receiver": "0x1c18a3", 
                "sender": "0x3aac67"
            }
        ]
    }, 
    {
        "hash": "0xf4e16b", 
        "number": 1, 
        "prevhash": "0xba5b35", 
        "transfers": [
            {
                "amount": 61, 
                "receiver": "0x4fd760", 
                "sender": "0x6d7beb"
            }, 
            {
                "amount": 2, 
                "receiver": "0x79a6f2", 
                "sender": "0x4d57fe"
            }
        ]
    }, 
    {
        "hash": "0x088df4", 
        "number": 1, 
        "prevhash": "0xba5b35", 
        "transfers": [
            {
                "amount": 14, 
                "receiver": "0xcb6398", 
                "sender": "0x76b8d4"
            }, 
            {
                "amount": 4, 
                "receiver": "0xa87234", 
                "sender": "0x0717d7"
            }, 
            {
                "amount": 30, 
                "receiver": "0xb78438", 
                "sender": "0xf193e8"
            }, 
            {
                "amount": 45, 
                "receiver": "0x161a68", 
                "sender": "0x2951d5"
            }
        ]
    }, 
    {
        "hash": "0x81f95a", 
        "number": 2, 
        "prevhash": "0x088df4", 
        "transfers": [
            {
                "amount": 34, 
                "receiver": "0x1a58d9", 
                "sender": "0x751267"
            }, 
            {
                "amount": 3, 
                "receiver": "0x958d42", 
                "sender": "0x3d2435"
            }, 
            {
                "amount": 51, 
                "receiver": "0x291c87", 
                "sender": "0x08fb43"
            }, 
            {
                "amount": 1, 
                "receiver": "0x87592c", 
                "sender": "0x525ab7"
            }, 
            {
                "amount": 11, 
                "receiver": "0xf6a75c", 
                "sender": "0xcb6398"
            }, 
            {
                "amount": 42, 
                "receiver": "0x79a6f2", 
                "sender": "0x659792"
            }
        ]
    }, 
    {
        "hash": "0x9ee24d", 
        "number": 1, 
        "prevhash": "0xba5b35", 
        "transfers": [
            {
                "amount": 14, 
                "receiver": "0xcb6398", 
                "sender": "0x76b8d4"
            }, 
            {
                "amount": 4, 
                "receiver": "0xa87234", 
                "sender": "0x0717d7"
            }, 
            {
                "amount": 8, 
                "receiver": "0x132118", 
                "sender": "0x3c794f"
            }, 
            {
                "amount": 14, 
                "receiver": "0x0334ee", 
                "sender": "0x958d15"
            }
        ]
    }, 
    {
        "hash": "0x0406fb", 
        "number": 2, 
        "prevhash": "0x9ee24d", 
        "transfers": [
            {
                "amount": 34, 
                "receiver": "0x1a58d9", 
                "sender": "0x751267"
            }, 
            {
                "amount": 3, 
                "receiver": "0x958d42", 
                "sender": "0x3d2435"
            }, 
            {
                "amount": 51, 
                "receiver": "0x291c87", 
                "sender": "0x08fb43"
            }, 
            {
                "amount": 67, 
                "receiver": "0x4cfca6", 
                "sender": "0xa210f3"
            }, 
            {
                "amount": 27, 
                "receiver": "0xc49bd5", 
                "sender": "0x7ea922"
            }, 
            {
                "amount": 36, 
                "receiver": "0x7ea922", 
                "sender": "0xf6c43c"
            }, 
            {
                "amount": 8, 
                "receiver": "0x6c905a", 
                "sender": "0xdee16f"
            }
        ]
    }, 
    {
        "hash": "0xd71c94", 
        "number": 3, 
        "prevhash": "0x0406fb", 
        "transfers": [
            {
                "amount": 70, 
                "receiver": "0xa2a728", 
                "sender": "0x8e0f45"
            }, 
            {
                "amount": 20, 
                "receiver": "0xde0a13", 
                "sender": "0xc6ffd9"
            }, 
            {
                "amount": 18, 
                "receiver": "0x112a6c", 
                "sender": "0x132118"
            }, 
            {
                "amount": 47, 
                "receiver": "0x93a797", 
                "sender": "0xf193e8"
            }, 
            {
                "amount": 9, 
                "receiver": "0xdee16f", 
                "sender": "0x2951d5"
            }, 
            {
                "amount": 10, 
                "receiver": "0x4cfca6", 
                "sender": "0xbee2de"
            }, 
            {
                "amount": 93, 
                "receiver": "0x0b87e9", 
                "sender": "0x93a797"
            }, 
            {
                "amount": 36, 
                "receiver": "0x297956", 
                "sender": "0x8416c3"
            }
        ]
    }, 
    {
        "hash": "0xd61d99", 
        "number": 2, 
        "prevhash": "0x9ee24d", 
        "transfers": [
            {
                "amount": 34, 
                "receiver": "0x1a58d9", 
                "sender": "0x751267"
            }, 
            {
                "amount": 3, 
                "receiver": "0x958d42", 
                "sender": "0x3d2435"
            }, 
            {
                "amount": 51, 
                "receiver": "0x291c87", 
                "sender": "0x08fb43"
            }
        ]
    }, 
    {
        "hash": "0xb3e58b", 
        "number": 3, 
        "prevhash": "0xd61d99", 
        "transfers": [
            {
                "amount": 70, 
                "receiver": "0xa2a728", 
                "sender": "0x8e0f45"
            }, 
            {
                "amount": 20, 
                "receiver": "0xde0a13", 
                "sender": "0xc6ffd9"
            }, 
            {
                "amount": 18, 
                "receiver": "0x112a6c", 
                "sender": "0x132118"
            }, 
            {
                "amount": 47, 
                "receiver": "0x93a797", 
                "sender": "0xf193e8"
            }, 
            {
                "amount": 59, 
                "receiver": "0x4d57fe", 
                "sender": "0x3d2435"
            }, 
            {
                "amount": 13, 
                "receiver": "0x0717d7", 
                "sender": "0x751267"
            }
        ]
    }, 
    {
        "hash": "0x52175b", 
        "number": 4, 
        "prevhash": "0xb3e58b", 
        "transfers": [
            {
                "amount": 7, 
                "receiver": "0x0334ee", 
                "sender": "0x2e5ba8"
            }, 
            {
                "amount": 41, 
                "receiver": "0x6c905a", 
                "sender": "0x31da1a"
            }, 
            {
                "amount": 8, 
                "receiver": "0xf193e8", 
                "sender": "0xbee2de"
            }, 
            {
                "amount": 3, 
                "receiver": "0x192f56", 
                "sender": "0x751267"
            }, 
            {
                "amount": 2, 
                "receiver": "0x708308", 
                "sender": "0x58b2aa"
            }
        ]
    }, 
    {
        "hash": "0xaf9a18", 
        "number": 5, 
        "prevhash": "0x52175b", 
        "transfers": [
            {
                "amount": 73, 
                "receiver": "0x0a1928", 
                "sender": "0xf6a75c"
            }, 
            {
                "amount": 29, 
                "receiver": "0xade9a4", 
                "sender": "0x02314c"
            }, 
            {
                "amount": 58, 
                "receiver": "0x91febb", 
                "sender": "0x1c18a3"
            }, 
            {
                "amount": 6, 
                "receiver": "0x1d500c", 
                "sender": "0x958d15"
            }, 
            {
                "amount": 43, 
                "receiver": "0x958d42", 
                "sender": "0x3ab154"
            }, 
            {
                "amount": 54, 
                "receiver": "0xebff4e", 
                "sender": "0x9f84a3"
            }, 
            {
                "amount": 10, 
                "receiver": "0x9f84a3", 
                "sender": "0xf2bdb0"
            }, 
            {
                "amount": 10, 
                "receiver": "0x3c794f", 
                "sender": "0x79a6f2"
            }, 
            {
                "amount": 2, 
                "receiver": "0x23f30f", 
                "sender": "0x751267"
            }, 
            {
                "amount": 77, 
                "receiver": "0xaf9152", 
                "sender": "0x4fd760"
            }
        ]
    }, 
    {
        "hash": "0x0b62fb", 
        "number": 4, 
        "prevhash": "0xb3e58b", 
        "transfers": [
            {
                "amount": 7, 
                "receiver": "0x0334ee", 
                "sender": "0x2e5ba8"
            }, 
            {
                "amount": 41, 
                "receiver": "0x6c905a", 
                "sender": "0x31da1a"
            }, 
            {
                "amount": 8, 
                "receiver": "0x3c794f", 
                "sender": "0xade9a4"
            }, 
            {
                "amount": 22, 
                "receiver": "0x9f84a3", 
                "sender": "0xb7e6b1"
            }, 
            {
                "amount": 53, 
                "receiver": "0x659792", 
                "sender": "0x0717d7"
            }, 
            {
                "amount": 1, 
                "receiver": "0x3e21b6", 
                "sender": "0xd8b894"
            }
        ]
    }, 
    {
        "hash": "0xc5fc6e", 
        "number": 1, 
        "prevhash": "0xba5b35", 
        "transfers": [
            {
                "amount": 38, 
                "receiver": "0xade9a4", 
                "sender": "0x1c18a3"
            }, 
            {
                "amount": 9, 
                "receiver": "0x751267", 
                "sender": "0x50853a"
            }, 
            {
                "amount": 9, 
                "receiver": "0xb51d18", 
                "sender": "0xa65b9a"
            }, 
            {
                "amount": 54, 
                "receiver": "0x0334ee", 
                "sender": "0xf6c43c"
            }, 
            {
                "amount": 43, 
                "receiver": "0x4d57fe", 
                "sender": "0xba84b6"
            }
        ]
    }, 
    {
        "hash": "0x5b3384", 
        "number": 1, 
        "prevhash": "0xba5b35", 
        "transfers": [
            {
                "amount": 4, 
                "receiver": "0x161a68", 
                "sender": "0xbd1a1b"
            }, 
            {
                "amount": 55, 
                "receiver": "0x93a797", 
                "sender": "0x23f30f"
            }, 
            {
                "amount": 11, 
                "receiver": "0x0334ee", 
                "sender": "0x9fde51"
            }, 
            {
                "amount": 26, 
                "receiver": "0x3aac67", 
                "sender": "0xb7e6b1"
            }, 
            {
                "amount": 13, 
                "receiver": "0xebff4e", 
                "sender": "0x66d178"
            }, 
            {
                "amount": 6, 
                "receiver": "0x8e0f45", 
                "sender": "0x192f56"
            }, 
            {
                "amount": 13, 
                "receiver": "0xa29662", 
                "sender": "0x31da1a"
            }
        ]
    }, 
    {
        "hash": "0x2e578b", 
        "number": 1, 
        "prevhash": "0xba5b35", 
        "transfers": [
            {
                "amount": 38, 
                "receiver": "0xade9a4", 
                "sender": "0x1c18a3"
            }, 
            {
                "amount": 9, 
                "receiver": "0x751267", 
                "sender": "0x50853a"
            }, 
            {
                "amount": 23, 
                "receiver": "0x87592c", 
                "sender": "0x379e95"
            }, 
            {
                "amount": 56, 
                "receiver": "0xa2a728", 
                "sender": "0xa210f3"
            }
        ]
    }, 
    {
        "hash": "0x2c15b1", 
        "number": 2, 
        "prevhash": "0x2e578b", 
        "transfers": [
            {
                "amount": 22, 
                "receiver": "0x08fb43", 
                "sender": "0x9f84a3"
            }, 
            {
                "amount": 22, 
                "receiver": "0x67cdcd", 
                "sender": "0x66d178"
            }
        ]
    }, 
    {
        "hash": "0xdeea1b", 
        "number": 3, 
        "prevhash": "0x2c15b1", 
        "transfers": [
            {
                "amount": 20, 
                "receiver": "0xc05730", 
                "sender": "0x86730f"
            }, 
            {
                "amount": 5, 
                "receiver": "0x3ab154", 
                "sender": "0xbee2de"
            }, 
            {
                "amount": 1, 
                "receiver": "0xb51d18", 
                "sender": "0xf2bdb0"
            }, 
            {
                "amount": 12, 
                "receiver": "0x6d81d2", 
                "sender": "0x3e21b6"
            }
        ]
    }, 
    {
        "hash": "0xa73d0b", 
        "number": 3, 
        "prevhash": "0x2c15b1", 
        "transfers": [
            {
                "amount": 22, 
                "receiver": "0xa29662", 
                "sender": "0xb51d18"
            }, 
            {
                "amount": 2, 
                "receiver": "0x86730f", 
                "sender": "0x708308"
            }, 
            {
                "amount": 93, 
                "receiver": "0xb8e965", 
                "sender": "0x6d7beb"
            }
        ]
    }, 
    {
        "hash": "0xd34750", 
        "number": 4, 
        "prevhash": "0xa73d0b", 
        "transfers": []
    }, 
    {
        "hash": "0xc2d773", 
        "number": 5, 
        "prevhash": "0xd34750", 
        "transfers": [
            {
                "amount": 45, 
                "receiver": "0x3c794f", 
                "sender": "0xf6c43c"
            }
        ]
    }, 
    {
        "hash": "0xa91b35", 
        "number": 5, 
        "prevhash": "0xd34750", 
        "transfers": []
    }, 
    {
        "hash": "0x643324", 
        "number": 6, 
        "prevhash": "0xa91b35", 
        "transfers": [
            {
                "amount": 93, 
                "receiver": "0x3c794f", 
                "sender": "0xb8e965"
            }, 
            {
                "amount": 24, 
                "receiver": "0x6d81d2", 
                "sender": "0x6c905a"
            }
        ]
    }, 
    {
        "hash": "0xc0c342", 
        "number": 7, 
        "prevhash": "0x643324", 
        "transfers": [
            {
                "amount": 18, 
                "receiver": "0x31e37d", 
                "sender": "0x56929c"
            }, 
            {
                "amount": 27, 
                "receiver": "0x2336fe", 
                "sender": "0xf6c43c"
            }, 
            {
                "amount": 52, 
                "receiver": "0xbd1a1b", 
                "sender": "0x28de1d"
            }, 
            {
                "amount": 1, 
                "receiver": "0xb78438", 
                "sender": "0xdfd5f9"
            }, 
            {
                "amount": 26, 
                "receiver": "0x66d178", 
                "sender": "0x4fd760"
            }, 
            {
                "amount": 27, 
                "receiver": "0x9f84a3", 
                "sender": "0x76b8d4"
            }, 
            {
                "amount": 54, 
                "receiver": "0xcb6398", 
                "sender": "0x0717d7"
            }
        ]
    }, 
    {
        "hash": "0xdf556a", 
        "number": 8, 
        "prevhash": "0xc0c342", 
        "transfers": [
            {
                "amount": 73, 
                "receiver": "0x28de1d", 
                "sender": "0x6071a6"
            }, 
            {
                "amount": 31, 
                "receiver": "0xaf9152", 
                "sender": "0x0717d7"
            }, 
            {
                "amount": 39, 
                "receiver": "0x6d7beb", 
                "sender": "0x31da1a"
            }, 
            {
                "amount": 57, 
                "receiver": "0x708308", 
                "sender": "0x3c794f"
            }, 
            {
                "amount": 15, 
                "receiver": "0x379e95", 
                "sender": "0xb51d18"
            }, 
            {
                "amount": 22, 
                "receiver": "0xc6ffd9", 
                "sender": "0x23f30f"
            }, 
            {
                "amount": 32, 
                "receiver": "0x9f84a3", 
                "sender": "0xba84b6"
            }, 
            {
                "amount": 10, 
                "receiver": "0xbd1a1b", 
                "sender": "0xc05730"
            }, 
            {
                "amount": 19, 
                "receiver": "0xc05730", 
                "sender": "0xade9a4"
            }, 
            {
                "amount": 4, 
                "receiver": "0x02314c", 
                "sender": "0x297956"
            }
        ]
    }, 
    {
        "hash": "0x701f31", 
        "number": 7, 
        "prevhash": "0x643324", 
        "transfers": [
            {
                "amount": 18, 
                "receiver": "0x31e37d", 
                "sender": "0x56929c"
            }, 
            {
                "amount": 27, 
                "receiver": "0x2336fe", 
                "sender": "0xf6c43c"
            }, 
            {
                "amount": 52, 
                "receiver": "0xbd1a1b", 
                "sender": "0x28de1d"
            }
        ]
    }, 
    {
        "hash": "0x0db8a3", 
        "number": 8, 
        "prevhash": "0x701f31", 
        "transfers": [
            {
                "amount": 73, 
                "receiver": "0x28de1d", 
                "sender": "0x6071a6"
            }, 
            {
                "amount": 31, 
                "receiver": "0xaf9152", 
                "sender": "0x0717d7"
            }, 
            {
                "amount": 39, 
                "receiver": "0x6d7beb", 
                "sender": "0x31da1a"
            }, 
            {
                "amount": 57, 
                "receiver": "0x708308", 
                "sender": "0x3c794f"
            }, 
            {
                "amount": 15, 
                "receiver": "0x379e95", 
                "sender": "0xb51d18"
            }, 
            {
                "amount": 13, 
                "receiver": "0x4fd760", 
                "sender": "0x58b2aa"
            }, 
            {
                "amount": 3, 
                "receiver": "0x56929c", 
                "sender": "0xd8b894"
            }, 
            {
                "amount": 26, 
                "receiver": "0x3e21b6", 
                "sender": "0x0717d7"
            }, 
            {
                "amount": 20, 
                "receiver": "0xcb6398", 
                "sender": "0x28de1d"
            }, 
            {
                "amount": 25, 
                "receiver": "0x958d15", 
                "sender": "0x3ab154"
            }
        ]
    }, 
    {
        "hash": "0x273130", 
        "number": 9, 
        "prevhash": "0x0db8a3", 
        "transfers": [
            {
                "amount": 2, 
                "receiver": "0x2f23d6", 
                "sender": "0x525ab7"
            }, 
            {
                "amount": 11, 
                "receiver": "0x50853a", 
                "sender": "0xbee2de"
            }, 
            {
                "amount": 85, 
                "receiver": "0x297956", 
                "sender": "0x0334ee"
            }
        ]
    }, 
    {
        "hash": "0xdf19c5", 
        "number": 8, 
        "prevhash": "0x701f31", 
        "transfers": [
            {
                "amount": 73, 
                "receiver": "0x28de1d", 
                "sender": "0x6071a6"
            }, 
            {
                "amount": 31, 
                "receiver": "0xaf9152", 
                "sender": "0x0717d7"
            }, 
            {
                "amount": 39, 
                "receiver": "0x6d7beb", 
                "sender": "0x31da1a"
            }, 
            {
                "amount": 57, 
                "receiver": "0x708308", 
                "sender": "0x3c794f"
            }, 
            {
                "amount": 15, 
                "receiver": "0x379e95", 
                "sender": "0xb51d18"
            }, 
            {
                "amount": 9, 
                "receiver": "0xa65b9a", 
                "sender": "0x7e02f2"
            }, 
            {
                "amount": 3, 
                "receiver": "0xf6a75c", 
                "sender": "0x2951d5"
            }
        ]
    }, 
    {
        "hash": "0x05911b", 
        "number": 6, 
        "prevhash": "0xa91b35", 
        "transfers": [
            {
                "amount": 7, 
                "receiver": "0x32580a", 
                "sender": "0x2f23d6"
            }, 
            {
                "amount": 45, 
                "receiver": "0x0334ee", 
                "sender": "0xbd1a1b"
            }, 
            {
                "amount": 2, 
                "receiver": "0x79a6f2", 
                "sender": "0x271f93"
            }, 
            {
                "amount": 52, 
                "receiver": "0xb8e965", 
                "sender": "0x4fd760"
            }, 
            {
                "amount": 46, 
                "receiver": "0x67cdcd", 
                "sender": "0xade9a4"
            }, 
            {
                "amount": 65, 
                "receiver": "0x291c87", 
                "sender": "0x7e02f2"
            }, 
            {
                "amount": 5, 
                "receiver": "0x708308", 
                "sender": "0xa65b9a"
            }, 
            {
                "amount": 12, 
                "receiver": "0x87592c", 
                "sender": "0x56929c"
            }
        ]
    }, 
    {
        "hash": "0x101ad4", 
        "number": 7, 
        "prevhash": "0x05911b", 
        "transfers": [
            {
                "amount": 29, 
                "receiver": "0xf6a75c", 
                "sender": "0x86730f"
            }, 
            {
                "amount": 24, 
                "receiver": "0x2951d5", 
                "sender": "0xf6c43c"
            }, 
            {
                "amount": 94, 
                "receiver": "0x291c87", 
                "sender": "0xba84b6"
            }, 
            {
                "amount": 30, 
                "receiver": "0x56929c", 
                "sender": "0x28de1d"
            }
        ]
    }, 
    {
        "hash": "0x7cf862", 
        "number": 6, 
        "prevhash": "0xa91b35", 
        "transfers": [
            {
                "amount": 7, 
                "receiver": "0x32580a", 
                "sender": "0x2f23d6"
            }, 
            {
                "amount": 45, 
                "receiver": "0x0334ee", 
                "sender": "0xbd1a1b"
            }, 
            {
                "amount": 2, 
                "receiver": "0x79a6f2", 
                "sender": "0x271f93"
            }, 
            {
                "amount": 52, 
                "receiver": "0xb8e965", 
                "sender": "0x4fd760"
            }
        ]
    }, 
    {
        "hash": "0xc80e60", 
        "number": 7, 
        "prevhash": "0x7cf862", 
        "transfers": [
            {
                "amount": 29, 
                "receiver": "0xf6a75c", 
                "sender": "0x86730f"
            }, 
            {
                "amount": 24, 
                "receiver": "0x2951d5", 
                "sender": "0xf6c43c"
            }, 
            {
                "amount": 28, 
                "receiver": "0xb8e965", 
                "sender": "0x86730f"
            }, 
            {
                "amount": 48, 
                "receiver": "0x83dd3a", 
                "sender": "0x8a1c55"
            }, 
            {
                "amount": 3, 
                "receiver": "0x8e0f45", 
                "sender": "0x2336fe"
            }, 
            {
                "amount": 49, 
                "receiver": "0x0b87e9", 
                "sender": "0x2e5ba8"
            }
        ]
    }, 
    {
        "hash": "0x1e1c6b", 
        "number": 8, 
        "prevhash": "0xc80e60", 
        "transfers": [
            {
                "amount": 2, 
                "receiver": "0x93a797", 
                "sender": "0x79a6f2"
            }
        ]
    }, 
    {
        "hash": "0x93a3fd", 
        "number": 8, 
        "prevhash": "0xc80e60", 
        "transfers": [
            {
                "amount": 3, 
                "receiver": "0xc05730", 
                "sender": "0x50853a"
            }, 
            {
                "amount": 3, 
                "receiver": "0x02314c", 
                "sender": "0xc49bd5"
            }, 
            {
                "amount": 60, 
                "receiver": "0x3d2435", 
                "sender": "0xb7e6b1"
            }
        ]
    }, 
    {
        "hash": "0xa5ac4e", 
        "number": 9, 
        "prevhash": "0x93a3fd", 
        "transfers": [
            {
                "amount": 48, 
                "receiver": "0xdfd5f9", 
                "sender": "0x7ea922"
            }, 
            {
                "amount": 10, 
                "receiver": "0x7e02f2", 
                "sender": "0x66d178"
            }, 
            {
                "amount": 55, 
                "receiver": "0x02314c", 
                "sender": "0x751267"
            }, 
            {
                "amount": 45, 
                "receiver": "0x958d42", 
                "sender": "0x31da1a"
            }, 
            {
                "amount": 7, 
                "receiver": "0x132118", 
                "sender": "0xa87234"
            }, 
            {
                "amount": 1, 
                "receiver": "0x112a6c", 
                "sender": "0x66d178"
            }, 
            {
                "amount": 9, 
                "receiver": "0xf6c43c", 
                "sender": "0x958d15"
            }
        ]
    }, 
    {
        "hash": "0xeebb6a", 
        "number": 8, 
        "prevhash": "0xc80e60", 
        "transfers": [
            {
                "amount": 3, 
                "receiver": "0xc05730", 
                "sender": "0x50853a"
            }, 
            {
                "amount": 3, 
                "receiver": "0xfaf2c4", 
                "sender": "0xf0ef5d"
            }, 
            {
                "amount": 4, 
                "receiver": "0x958d42", 
                "sender": "0xade9a4"
            }
        ]
    }, 
    {
        "hash": "0x6c36f1", 
        "number": 7, 
        "prevhash": "0x7cf862", 
        "transfers": [
            {
                "amount": 9, 
                "receiver": "0xdfd5f9", 
                "sender": "0xbee2de"
            }, 
            {
                "amount": 14, 
                "receiver": "0x161a68", 
                "sender": "0x79a6f2"
            }, 
            {
                "amount": 7, 
                "receiver": "0x297956", 
                "sender": "0x958d15"
            }, 
            {
                "amount": 6, 
                "receiver": "0x3d2435", 
                "sender": "0xd8b894"
            }
        ]
    }, 
    {
        "hash": "0x1ff9a3", 
        "number": 8, 
        "prevhash": "0x6c36f1", 
        "transfers": [
            {
                "amount": 3, 
                "receiver": "0xc05730", 
                "sender": "0x50853a"
            }
        ]
    }, 
    {
        "hash": "0xe99119", 
        "number": 8, 
        "prevhash": "0x6c36f1", 
        "transfers": [
            {
                "amount": 69, 
                "receiver": "0x2336fe", 
                "sender": "0x161a68"
            }, 
            {
                "amount": 6, 
                "receiver": "0xd8b894", 
                "sender": "0x32580a"
            }, 
            {
                "amount": 39, 
                "receiver": "0xebff4e", 
                "sender": "0xdac5bd"
            }, 
            {
                "amount": 47, 
                "receiver": "0xbee2de", 
                "sender": "0x7ea922"
            }, 
            {
                "amount": 77, 
                "receiver": "0x66d178", 
                "sender": "0x2e5ba8"
            }, 
            {
                "amount": 15, 
                "receiver": "0x6c905a", 
                "sender": "0xb78438"
            }, 
            {
                "amount": 33, 
                "receiver": "0x31da1a", 
                "sender": "0xade9a4"
            }, 
            {
                "amount": 10, 
                "receiver": "0x192f56", 
                "sender": "0x67cdcd"
            }
        ]
    }, 
    {
        "hash": "0x8ad495", 
        "number": 9, 
        "prevhash": "0xe99119", 
        "transfers": [
            {
                "amount": 32, 
                "receiver": "0x4d57fe", 
                "sender": "0xaf9152"
            }, 
            {
                "amount": 26, 
                "receiver": "0xde0a13", 
                "sender": "0x659792"
            }, 
            {
                "amount": 1, 
                "receiver": "0x8a1c55", 
                "sender": "0xcb6398"
            }, 
            {
                "amount": 18, 
                "receiver": "0x7ea922", 
                "sender": "0x56929c"
            }, 
            {
                "amount": 19, 
                "receiver": "0xa210f3", 
                "sender": "0xc05730"
            }
        ]
    }, 
    {
        "hash": "0x4ca668", 
        "number": 10, 
        "prevhash": "0x8ad495", 
        "transfers": []
    }
]
